batting_order_analysis/__init__.py
batting_order_analysis/lineup.py
batting_order_analysis/player.py
batting_order_analysis/simulation.py
batting_order_analysis/data/stats.csv
batting_order_analysis/data/pa_outcomes/giants_outcomes.txt
batting_order_analysis/data/teams/astros.txt
batting_order_analysis/data/teams/dodgers.txt
batting_order_analysis/data/teams/giants.txt
batting_order_analysis/data/teams/pirates.txt
batting_order_analysis-0.0.52.dist-info/LICENSE
batting_order_analysis-0.0.52.dist-info/METADATA
batting_order_analysis-0.0.52.dist-info/WHEEL
batting_order_analysis-0.0.52.dist-info/top_level.txt
batting_order_analysis-0.0.52.dist-info/RECORD
