Metadata-Version: 2.1
Name: batting-order-analysis
Version: 0.0.52
Summary: Analysis of different batting orders given a lineup
Home-page: https://github.com/drewscottt/batting_order_analysis
Author: Drew Scott
Author-email: drewscott1103@gmail.com
License: UNKNOWN
Platform: UNKNOWN
Classifier: Programming Language :: Python :: 3
Classifier: License :: OSI Approved :: MIT License
Classifier: Operating System :: OS Independent
Requires-Python: >=3.6
License-File: LICENSE
Requires-Dist: tqdm
